dima.py
dima_db-1.0.0.dist-info/LICENSE
dima_db-1.0.0.dist-info/METADATA
dima_db-1.0.0.dist-info/WHEEL
dima_db-1.0.0.dist-info/entry_points.txt
dima_db-1.0.0.dist-info/top_level.txt
dima_db-1.0.0.dist-info/RECORD
