Metadata-Version: 2.1
Name: dima-db
Version: 1.0.0
Summary: CLI to view and kill running queries in postgres
Home-page: UNKNOWN
Author: Matthew Ruttley
Author-email: matt@frame.io
License: MIT License
